{
  "id": 608,
  "name": "Global Hunt",
  "description": "Globla hunt work through Talent Workforce Solutions; Recruitment Process Outsourcing, Executive Recruitment, IT staffing and Outplacement, GlobalHunt has become a prime partner for business excellence. The commitment to convert client strategies into realistic innovation, GlobalHunt transforms talent requisite into performance. With its global presence GlobalHunt optimizes talent resources towards business impacting solutions.",
  "features": [
    "Deal with a wide range of companies",
    "Provide outplacement solutions",
    "Work with media platforms"
  ],
  "founders": [],
  "price": [],
  "business_objectives": [
    "Boost Hiring Manager Confidence and Productivity",
    "Hire Top Talent Faster and More Efficiently"
  ],
  "categories": [
    "Recruiting",
    "Talent Management"
  ],
  "sub_categories": [
    "Recruiting software",
    "Staffing & management software",
    "HR management suites"
  ],
  "tags": [
    "Recruiting",
    "Hiring",
    "Talent sourcing",
    "Recruiting costs",
    ""
  ],
  "headquarter": "Noida, Uttar Pradesh",
  "launch_date": "2002",
  "order": 20566,
  "weightage": null,
  "HCM": null,
  "Headline": "The Complete Recruitment Services",
  "ProductId": null,
  "ShortDescription": "GlobalHunt is a global talent advisory firm that works to deliver people, as right resource.",
  "Company": [],
  "CrossSells": [],
  "DemoDetails": {
    "title": "",
    "videos": []
  },
  "HCM_INTEGRATION": [],
  "Highlights": [],
  "Approved": false,
  "Claimed": false,
  "Demo_Available": false,
  "Global_Enterprise": false,
  "Large_Enterprise": false,
  "Small_Enterprise": false,
  "Main_Home": null,
  "Most_Searched": false,
  "New_Arrival": false,
  "Normal": true,
  "Pricing_Available": false,
  "Saved": false,
  "Sponsored": false,
  "Spotlight": false,
  "PublishedAt": "2024-02-28T06:30:59.479Z",
  "enhanced_description": "Global Hunt is a global talent advisory firm that provides complete recruitment services, including Recruitment Process Outsourcing (RPO), Executive Recruitment, IT staffing, and Outplacement solutions. As a prime partner for business excellence, Global Hunt works to deliver the right talent, transforming client talent requirements into performance and optimizing talent resources towards business-impacting solutions with its global presence. They deal with a wide range of companies and work with media platforms to support their talent workforce solutions.",
  "key_use_cases": [
    "Recruitment Process Outsourcing (RPO)",
    "Executive recruitment",
    "IT staffing",
    "Outplacement solutions",
    "Talent advisory services",
    "Optimizing talent resources for business solutions"
  ],
  "competitive_advantages": [
    "Global presence as a talent advisory firm",
    "Offers complete recruitment services",
    "Transforms client talent requisites into performance",
    "Optimizes talent resources towards business impacting solutions",
    "Acts as a prime partner for business excellence",
    "Deals with a wide range of companies"
  ],
  "hr_functions_supported": [
    "Recruiting",
    "Talent Management",
    "Staffing",
    "Outplacement",
    "Workforce solutions"
  ],
  "roi_benefits": [
    "Boost Hiring Manager Confidence and Productivity",
    "Hire Top Talent Faster and More Efficiently",
    "Optimize talent resources towards business impacting solutions",
    "Transform talent requisite into performance"
  ],
  "searchable_keywords": [
    "Global Hunt",
    "Talent Workforce Solutions",
    "Recruitment Process Outsourcing",
    "Executive Recruitment",
    "IT staffing",
    "Outplacement",
    "Recruiting",
    "Talent Management",
    "Hiring",
    "Talent sourcing",
    "Recruiting costs",
    "Recruitment services",
    "Global talent advisory firm",
    "Right resource",
    "Recruiting software",
    "Staffing & management software",
    "HR management suites"
  ],
  "primary_users": [
    "Hiring Managers",
    "Companies seeking talent solutions"
  ],
  "_weight": 1
}