{
  "id": 613,
  "name": "Globallogic",
  "description": "We help our clients design and build innovative products, platforms, and digital experiences for the modern world. By integrating our strategic design, complex engineering, and vertical industry expertise with Hitachi\u2019s Operating Technology and Information Technology capabilities, we help our clients imagine what\u2019s possible and accelerate their transition into tomorrow\u2019s digital businesses. We help our clients design and build innovative products, platforms, and digital experiences for the modern world. By integrating our strategic design, complex engineering, and vertical industry expertise with Hitachi\u2019s Operating Technology and Information Technology capabilities, we help our clients imagine what\u2019s possible and accelerate their transition into tomorrow\u2019s digital businesses.",
  "features": [
    "Full-Lifecycle Product Development Services",
    "Wide range of services provider",
    "Data warehouse"
  ],
  "founders": [],
  "price": [],
  "business_objectives": [
    "Build a More Diverse and Inclusive Workforce"
  ],
  "categories": [
    "Talent Management",
    "Recruiting",
    "Other / technology"
  ],
  "sub_categories": [
    "Workforce management",
    "HR management suites",
    "Recruitment agencies",
    "HR consulting providers",
    "Recruiting automation software",
    "Software and Services Related to HR Software",
    "Recruiting software"
  ],
  "tags": [
    "Workforce diversity",
    "Employee diversity"
  ],
  "headquarter": "Santa Clara ,USA",
  "launch_date": "2000",
  "order": 20570,
  "weightage": null,
  "HCM": null,
  "Headline": "Smart. Bold. Human",
  "ProductId": null,
  "ShortDescription": "GlobalLogic, a Hitachi Group Company, is a full-lifecycle product development services leader.",
  "Company": [],
  "CrossSells": [],
  "DemoDetails": {
    "title": "",
    "videos": []
  },
  "HCM_INTEGRATION": [],
  "Highlights": [],
  "Approved": false,
  "Claimed": false,
  "Demo_Available": false,
  "Global_Enterprise": false,
  "Large_Enterprise": false,
  "Small_Enterprise": false,
  "Main_Home": null,
  "Most_Searched": false,
  "New_Arrival": false,
  "Normal": true,
  "Pricing_Available": false,
  "Saved": false,
  "Sponsored": false,
  "Spotlight": false,
  "PublishedAt": "2024-02-28T06:31:07.898Z",
  "enhanced_description": "GlobalLogic, a Hitachi Group Company, specializes in full-lifecycle product development services. They assist clients in designing and building innovative products, platforms, and digital experiences for the modern world. This is achieved by integrating their strategic design, complex engineering, and vertical industry expertise with Hitachi\u2019s Operating Technology and Information Technology capabilities. Their primary objective is to accelerate clients' transition into tomorrow\u2019s digital businesses, including supporting key business objectives such as building a more diverse and inclusive workforce.",
  "key_use_cases": [
    "Design and build innovative digital products and platforms",
    "Develop digital experiences for modern businesses",
    "Accelerate transition into digital businesses",
    "Support initiatives to build a more diverse and inclusive workforce",
    "Provide HR consulting services",
    "Develop or integrate recruiting automation software",
    "Support or develop HR management suites"
  ],
  "competitive_advantages": [
    "Integration with Hitachi's Operating Technology (OT) and Information Technology (IT) capabilities",
    "Leadership in full-lifecycle product development services",
    "Expertise in strategic design, complex engineering, and various vertical industries",
    "Offers a wide range of services",
    "Backed by Hitachi Group Company resources and reputation"
  ],
  "hr_functions_supported": [
    "Talent Management",
    "Recruiting",
    "Workforce Management",
    "HR Consulting",
    "Diversity & Inclusion (D&I)"
  ],
  "technology_stack": [
    "Hitachi Operating Technology capabilities",
    "Hitachi Information Technology capabilities",
    "Data warehouse technologies"
  ],
  "roi_benefits": [
    "Accelerated transition to digital business",
    "Enhanced capability to design and build innovative products and platforms",
    "Achievement of diversity and inclusion objectives within the workforce"
  ],
  "searchable_keywords": [
    "Globallogic",
    "product development",
    "digital transformation",
    "digital experiences",
    "platforms",
    "strategic design",
    "complex engineering",
    "vertical industry expertise",
    "Hitachi",
    "Operating Technology",
    "Information Technology",
    "data warehouse",
    "talent management",
    "recruiting",
    "workforce management",
    "HR management suites",
    "recruitment agencies",
    "HR consulting",
    "recruiting automation",
    "HR software",
    "workforce diversity",
    "employee diversity",
    "digital business",
    "full-lifecycle product development",
    "technology services"
  ],
  "primary_users": [
    "Digital Business Leaders",
    "Product Development Leaders",
    "HR Leaders (e.g., Head of Talent, Head of Recruiting, CHRO)",
    "IT Leaders",
    "Business Owners / Executives driving digital transformation"
  ],
  "_weight": 1
}