{
  "id": 993,
  "name": "Photon",
  "description": "We work with 40% of the Fortune 100 on their Digital initiatives and are known for our ability to integrate Strategy Consulting, Creative Design, and Technology at scale. Please visit www.photon.com to learn more about us, how we work, and our customer case studies.",
  "features": [
    "Help to Scale globally",
    "Provide UI-UX support",
    "Work with AI and ML"
  ],
  "founders": [],
  "price": [],
  "business_objectives": [
    "Accelerate Skill Development and Learning Efficiency"
  ],
  "categories": [
    "Other / technology"
  ],
  "sub_categories": [
    "Artificial intelligence",
    "Internet of things"
  ],
  "tags": [
    "Learning efficiency",
    "Skill acquisition",
    "Personalised learning"
  ],
  "headquarter": "Chennai",
  "launch_date": "2007",
  "order": 20939,
  "weightage": null,
  "HCM": null,
  "Headline": "Making Tomorrow Happen Today",
  "ProductId": null,
  "ShortDescription": "Photon.com has emerged as one of the world\u2019s largest and fastest-growing Digital Agencies.",
  "Company": [],
  "CrossSells": [],
  "DemoDetails": {
    "title": "",
    "videos": []
  },
  "HCM_INTEGRATION": [],
  "Highlights": [],
  "Approved": false,
  "Claimed": false,
  "Demo_Available": false,
  "Global_Enterprise": false,
  "Large_Enterprise": false,
  "Small_Enterprise": false,
  "Main_Home": null,
  "Most_Searched": false,
  "New_Arrival": false,
  "Normal": true,
  "Pricing_Available": false,
  "Saved": false,
  "Sponsored": false,
  "Spotlight": false,
  "PublishedAt": "2024-02-28T06:38:25.438Z",
  "enhanced_description": "Photon is one of the world's largest and fastest-growing Digital Agencies, working with 40% of the Fortune 100 on their Digital initiatives. They are known for their ability to integrate Strategy Consulting, Creative Design, and Technology at scale. Their expertise includes UI-UX support, AI, and ML, with a focus on accelerating skill development and learning efficiency.",
  "ideal_company_sizes": [
    "Large Enterprise",
    "Global Enterprise"
  ],
  "key_use_cases": [
    "Digital transformation initiatives",
    "Strategy consulting for digital projects",
    "Creative design and UI-UX support",
    "Technology integration at scale",
    "AI and ML development and implementation",
    "Accelerating skill development programs",
    "Enhancing learning efficiency",
    "Developing personalized learning solutions"
  ],
  "competitive_advantages": [
    "Extensive experience with Fortune 100 companies",
    "Integrated approach combining strategy, design, and technology",
    "Global scale and position as a large digital agency"
  ],
  "implementation_scenarios": [
    "Project-based engagements for digital initiatives",
    "Custom digital solution development and deployment"
  ],
  "hr_functions_supported": [
    "Learning & Development"
  ],
  "technology_stack": [
    "Artificial intelligence (AI)",
    "Machine learning (ML)",
    "Internet of things (IoT)"
  ],
  "integration_capabilities": [
    "Technology integration (general)"
  ],
  "roi_benefits": [
    "Accelerated skill development",
    "Improved learning efficiency",
    "Support for global scalability"
  ],
  "searchable_keywords": [
    "Photon",
    "Digital agency",
    "Digital initiatives",
    "Strategy consulting",
    "Creative design",
    "Technology integration",
    "Global scale",
    "UI-UX support",
    "AI",
    "ML",
    "Artificial intelligence",
    "Machine learning",
    "Internet of things",
    "Skill development",
    "Learning efficiency",
    "Skill acquisition",
    "Personalised learning"
  ],
  "primary_users": [
    "Client executives",
    "IT leadership",
    "Learning & Development professionals",
    "Business stakeholders"
  ],
  "scalability_features": [
    "Support for global scaling",
    "Ability to integrate technology at scale"
  ],
  "_weight": 1
}